notebook/__init__.py
notebook/__main__.py
notebook/_sysinfo.py
notebook/_tz.py
notebook/_version.py
notebook/config_manager.py
notebook/conftest.py
notebook/extensions.py
notebook/jstest.py
notebook/log.py
notebook/nbextensions.py
notebook/notebookapp.py
notebook/serverextensions.py
notebook/traittypes.py
notebook/transutils.py
notebook/utils.py
notebook/auth/__init__.py
notebook/auth/__main__.py
notebook/auth/login.py
notebook/auth/logout.py
notebook/auth/security.py
notebook/auth/tests/__init__.py
notebook/auth/tests/test_login.py
notebook/auth/tests/test_security.py
notebook/base/__init__.py
notebook/base/handlers.py
notebook/base/zmqhandlers.py
notebook/bundler/__init__.py
notebook/bundler/__main__.py
notebook/bundler/bundlerextensions.py
notebook/bundler/handlers.py
notebook/bundler/tarball_bundler.py
notebook/bundler/tools.py
notebook/bundler/zip_bundler.py
notebook/bundler/tests/__init__.py
notebook/bundler/tests/test_bundler_api.py
notebook/bundler/tests/test_bundler_tools.py
notebook/bundler/tests/test_bundlerextension.py
notebook/bundler/tests/resources/empty.ipynb
notebook/bundler/tests/resources/another_subdir/test_file.txt
notebook/bundler/tests/resources/subdir/test_file.txt
notebook/bundler/tests/resources/subdir/subsubdir/.gitkeep
notebook/edit/__init__.py
notebook/edit/handlers.py
notebook/files/__init__.py
notebook/files/handlers.py
notebook/gateway/__init__.py
notebook/gateway/handlers.py
notebook/gateway/managers.py
notebook/i18n/__init__.py
notebook/i18n/fr_FR/LC_MESSAGES/nbjs.json
notebook/i18n/fr_FR/LC_MESSAGES/nbjs.po
notebook/i18n/fr_FR/LC_MESSAGES/nbui.mo
notebook/i18n/fr_FR/LC_MESSAGES/nbui.po
notebook/i18n/fr_FR/LC_MESSAGES/notebook.mo
notebook/i18n/fr_FR/LC_MESSAGES/notebook.po
notebook/i18n/ja_JP/LC_MESSAGES/nbjs.json
notebook/i18n/ja_JP/LC_MESSAGES/nbjs.po
notebook/i18n/ja_JP/LC_MESSAGES/nbui.mo
notebook/i18n/ja_JP/LC_MESSAGES/nbui.po
notebook/i18n/ja_JP/LC_MESSAGES/notebook.mo
notebook/i18n/ja_JP/LC_MESSAGES/notebook.po
notebook1-6.4.0.dev0.dist-info/LICENSE
notebook1-6.4.0.dev0.dist-info/METADATA
notebook1-6.4.0.dev0.dist-info/WHEEL
notebook1-6.4.0.dev0.dist-info/entry_points.txt
notebook1-6.4.0.dev0.dist-info/top_level.txt
notebook1-6.4.0.dev0.dist-info/RECORD
